aginet/__init__.py
aginet/aginet.py
aginet-0.2.dist-info/LICENSE
aginet-0.2.dist-info/METADATA
aginet-0.2.dist-info/WHEEL
aginet-0.2.dist-info/top_level.txt
aginet-0.2.dist-info/RECORD
