Metadata-Version: 2.1
Name: aginet
Version: 0.2
Summary: A Python SDK for interacting with AGInet
Home-page: https://github.com/operatorlabs/aginet-python
Author: Operator Labs
Author-email: kevin@operator.io
Classifier: Programming Language :: Python :: 3
Classifier: License :: OSI Approved :: MIT License
Classifier: Operating System :: OS Independent
Requires-Python: >=3.6
License-File: LICENSE
